cislunar/__init__.py
cislunar/core.py
cislunar-0.0.2.dist-info/LICENSE
cislunar-0.0.2.dist-info/METADATA
cislunar-0.0.2.dist-info/WHEEL
cislunar-0.0.2.dist-info/top_level.txt
cislunar-0.0.2.dist-info/RECORD
