Metadata-Version: 2.1
Name: cislunar
Version: 0.0.2
Summary: Cislunar Utility Toolkit
Author: Erin Lee Ryan
Classifier: Programming Language :: Python :: 3
Classifier: Operating System :: OS Independent
Requires-Python: >=3.6
License-File: LICENSE
Requires-Dist: numpy
Requires-Dist: pandas
Requires-Dist: fastapi
Requires-Dist: uvicorn
Requires-Dist: joblib
Requires-Dist: python-multipart
Requires-Dist: pydantic
